filelock/__init__.py
filelock/_api.py
filelock/_error.py
filelock/_soft.py
filelock/_unix.py
filelock/_util.py
filelock/_windows.py
filelock/asyncio.py
filelock/py.typed
filelock/version.py
filelock-3.15.2.dist-info/METADATA
filelock-3.15.2.dist-info/WHEEL
filelock-3.15.2.dist-info/licenses/LICENSE
filelock-3.15.2.dist-info/RECORD
