Metadata-Version: 2.3
Name: filelock
Version: 3.15.2
Summary: A platform independent file lock.
Project-URL: Documentation, https://py-filelock.readthedocs.io
Project-URL: Homepage, https://github.com/tox-dev/py-filelock
Project-URL: Source, https://github.com/tox-dev/py-filelock
Project-URL: Tracker, https://github.com/tox-dev/py-filelock/issues
Maintainer-email: Bernát Gábor <gaborjbernat@gmail.com>
License-Expression: Unlicense
License-File: LICENSE
Keywords: application,cache,directory,log,user
Classifier: Development Status :: 5 - Production/Stable
Classifier: Intended Audience :: Developers
Classifier: License :: OSI Approved :: The Unlicense (Unlicense)
Classifier: Operating System :: OS Independent
Classifier: Programming Language :: Python
Classifier: Programming Language :: Python :: 3 :: Only
Classifier: Programming Language :: Python :: 3.8
Classifier: Programming Language :: Python :: 3.9
Classifier: Programming Language :: Python :: 3.10
Classifier: Programming Language :: Python :: 3.11
Classifier: Programming Language :: Python :: 3.12
Classifier: Topic :: Internet
Classifier: Topic :: Software Development :: Libraries
Classifier: Topic :: System
Requires-Python: >=3.8
Provides-Extra: docs
Requires-Dist: furo>=2023.9.10; extra == 'docs'
Requires-Dist: sphinx-autodoc-typehints!=1.23.4,>=1.25.2; extra == 'docs'
Requires-Dist: sphinx>=7.2.6; extra == 'docs'
Provides-Extra: testing
Requires-Dist: covdefaults>=2.3; extra == 'testing'
Requires-Dist: coverage>=7.3.2; extra == 'testing'
Requires-Dist: diff-cover>=8.0.1; extra == 'testing'
Requires-Dist: pytest-asyncio>=0.21; extra == 'testing'
Requires-Dist: pytest-cov>=4.1; extra == 'testing'
Requires-Dist: pytest-mock>=3.12; extra == 'testing'
Requires-Dist: pytest-timeout>=2.2; extra == 'testing'
Requires-Dist: pytest>=7.4.3; extra == 'testing'
Provides-Extra: typing
Requires-Dist: typing-extensions>=4.8; (python_version < '3.11') and extra == 'typing'
